{
  "version": "7",
  "dialect": "postgresql",
  "entries": [
    {
      "idx": 0,
      "version": "7",
      "when": 1760293374438,
      "tag": "0000_ambiguous_inertia",
      "breakpoints": true
    },
    {
      "idx": 1,
      "version": "7",
      "when": 1761562373229,
      "tag": "0001_messy_penance",
      "breakpoints": true
    },
    {
      "idx": 2,
      "version": "7",
      "when": 1762950188238,
      "tag": "0002_calm_madripoor",
      "breakpoints": true
    },
    {
      "idx": 3,
      "version": "7",
      "when": 1762950298792,
      "tag": "0003_white_fenris",
      "breakpoints": true
    },
    {
      "idx": 4,
      "version": "7",
      "when": 1762950324146,
      "tag": "0004_tranquil_lockheed",
      "breakpoints": true
    },
    {
      "idx": 5,
      "version": "7",
      "when": 1763204815918,
      "tag": "0005_dizzy_millenium_guard",
      "breakpoints": true
    },
    {
      "idx": 6,
      "version": "7",
      "when": 1763226418806,
      "tag": "0006_misty_golden_guardian",
      "breakpoints": true
    },
    {
      "idx": 7,
      "version": "7",
      "when": 1763231397924,
      "tag": "0007_dizzy_centennial",
      "breakpoints": true
    },
    {
      "idx": 8,
      "version": "7",
      "when": 1763310067161,
      "tag": "0008_cheerful_bedlam",
      "breakpoints": true
    },
    {
      "idx": 9,
      "version": "7",
      "when": 1763578698477,
      "tag": "0009_brief_barracuda",
      "breakpoints": true
    },
    {
      "idx": 10,
      "version": "7",
      "when": 1763627326902,
      "tag": "0010_flaky_living_tribunal",
      "breakpoints": true
    },
    {
      "idx": 11,
      "version": "7",
      "when": 1763641593976,
      "tag": "0011_steep_menace",
      "breakpoints": true
    },
    {
      "idx": 12,
      "version": "7",
      "when": 1763702837694,
      "tag": "0012_cooing_magneto",
      "breakpoints": true
    },
    {
      "idx": 13,
      "version": "7",
      "when": 1763715516340,
      "tag": "0013_nifty_loners",
      "breakpoints": true
    },
    {
      "idx": 14,
      "version": "7",
      "when": 1763802629837,
      "tag": "0014_silly_agent_brand",
      "breakpoints": true
    },
    {
      "idx": 15,
      "version": "7",
      "when": 1763822878484,
      "tag": "0015_tearful_sebastian_shaw",
      "breakpoints": true
    },
    {
      "idx": 16,
      "version": "7",
      "when": 1763889018895,
      "tag": "0016_clammy_dust",
      "breakpoints": true
    },
    {
      "idx": 17,
      "version": "7",
      "when": 1764122035327,
      "tag": "0017_vengeful_rocket_raccoon",
      "breakpoints": true
    },
    {
      "idx": 18,
      "version": "7",
      "when": 1764122627240,
      "tag": "0018_clumsy_serpent_society",
      "breakpoints": true
    },
    {
      "idx": 19,
      "version": "7",
      "when": 1764336065435,
      "tag": "0019_crazy_blink",
      "breakpoints": true
    },
    {
      "idx": 20,
      "version": "7",
      "when": 1764336254386,
      "tag": "0020_minor_cloak",
      "breakpoints": true
    },
    {
      "idx": 21,
      "version": "7",
      "when": 1764837055396,
      "tag": "0021_needy_queen_noir",
      "breakpoints": true
    },
    {
      "idx": 22,
      "version": "7",
      "when": 1764853011776,
      "tag": "0022_fine_alex_power",
      "breakpoints": true
    },
    {
      "idx": 23,
      "version": "7",
      "when": 1764904046955,
      "tag": "0023_clever_junta",
      "breakpoints": true
    },
    {
      "idx": 24,
      "version": "7",
      "when": 1764906859117,
      "tag": "0024_noisy_mattie_franklin",
      "breakpoints": true
    },
    {
      "idx": 25,
      "version": "7",
      "when": 1764922670862,
      "tag": "0025_cute_shatterstar",
      "breakpoints": true
    },
    {
      "idx": 26,
      "version": "7",
      "when": 1764935314372,
      "tag": "0026_acoustic_nick_fury",
      "breakpoints": true
    },
    {
      "idx": 27,
      "version": "7",
      "when": 1765045712068,
      "tag": "0027_demonic_selene",
      "breakpoints": true
    }
  ]
}